arcadedb_python/__init__.py
arcadedb_python/exceptions.py
arcadedb_python/api/__init__.py
arcadedb_python/api/client.py
arcadedb_python/api/config.py
arcadedb_python/api/sync.py
arcadedb_python/dao/__init__.py
arcadedb_python/dao/database.py
arcadedb_python/model/__init__.py
arcadedb_python/model/database.py
arcadedb_python/model/request.py
arcadedb_python-0.3.1.dist-info/METADATA
arcadedb_python-0.3.1.dist-info/WHEEL
arcadedb_python-0.3.1.dist-info/licenses/LICENSE
arcadedb_python-0.3.1.dist-info/RECORD
