Metadata-Version: 2.4
Name: arcadedb-python
Version: 0.3.1
Summary: Python driver for ArcadeDB - Multi-Model Database with Graph, Document, Key-Value, Vector, and Time-Series support
Project-URL: Homepage, https://github.com/stevereiner/arcadedb-python
Project-URL: Documentation, https://docs.arcadedb.com/
Project-URL: Repository, https://github.com/stevereiner/arcadedb-python
Project-URL: Bug Tracker, https://github.com/stevereiner/arcadedb-python/issues
Project-URL: Changelog, https://github.com/stevereiner/arcadedb-python/blob/main/CHANGELOG.md
Author: Adams Rosales, ExtReMLapin, Steve Reiner
Maintainer: Steve Reiner
License-Expression: Apache-2.0
License-File: LICENSE
Keywords: arcadedb,database,document,graph,key-value,multi-model,nosql,python-driver,time-series,vector
Classifier: Development Status :: 4 - Beta
Classifier: Intended Audience :: Developers
Classifier: License :: OSI Approved :: Apache Software License
Classifier: Operating System :: OS Independent
Classifier: Programming Language :: Python :: 3
Classifier: Programming Language :: Python :: 3.10
Classifier: Programming Language :: Python :: 3.11
Classifier: Programming Language :: Python :: 3.12
Classifier: Programming Language :: Python :: 3.13
Classifier: Topic :: Database
Classifier: Topic :: Database :: Database Engines/Servers
Classifier: Topic :: Software Development :: Libraries :: Python Modules
Classifier: Typing :: Typed
Requires-Python: >=3.10
Requires-Dist: requests>=2.25.0
Requires-Dist: retry>=0.9.2
Provides-Extra: cypher
Requires-Dist: pygments>=2.0.0; extra == 'cypher'
Provides-Extra: dev
Requires-Dist: black>=23.0.0; extra == 'dev'
Requires-Dist: flake8>=6.0.0; extra == 'dev'
Requires-Dist: isort>=5.12.0; extra == 'dev'
Requires-Dist: mypy>=1.0.0; extra == 'dev'
Requires-Dist: pre-commit>=3.0.0; extra == 'dev'
Requires-Dist: pytest-cov>=4.0.0; extra == 'dev'
Requires-Dist: pytest-mock>=3.10.0; extra == 'dev'
Requires-Dist: pytest>=7.0.0; extra == 'dev'
Requires-Dist: tox>=4.0.0; extra == 'dev'
Provides-Extra: full
Requires-Dist: psycopg>=3.0.0; extra == 'full'
Requires-Dist: pygments>=2.0.0; extra == 'full'
Provides-Extra: postgresql
Requires-Dist: psycopg>=3.0.0; extra == 'postgresql'
